bil361-odev1/ozdemir.v
module ozdemir(
  input  wire        clk_i,
  input  wire        rst_i,
  input  wire [31:0] inst_i,
  output reg  [31:0] pc_o,
  output wire [1023:0] regs_o,
  output reg         data_mem_we_o,
  output reg  [31:0] data_mem_addr_o,
  output reg  [31:0] data_mem_wdata_o,
  input  wire [31:0] data_mem_rdata_i,
  output reg  [1:0]  cur_stage_o
);

  reg [31:0] pc_reg;
  reg [31:0] rfile[0:31];
  reg [31:0] instr;
  reg [1:0]  phase;

  reg [4:0]  rd_q, rs1_q, rs2_q;
  reg [31:0] rs1_val_q, rs2_val_q;
  reg [31:0] immI_q, immS_q, immB_q, immU_q, immJ_q;

  reg        is_load_q;
  reg        is_store_q;

  reg        ex_wb_en_q;
  reg [31:0] ex_result_q;
  reg        ex_pc_jump_q;
  reg [31:0] ex_pc_next_q;

  reg [7:0]  ex_left;
  reg [1:0]  srt_step_q;
  reg [1:0]  ldmax_step_q;
  reg [31:0] ldmax_rd_q, ldmax_rs1_q, ldmax_rs2_q;

  reg        mac_active;
  reg [31:0] mac_addr_accum, mac_addr_a, mac_addr_b;
  reg [31:0] mac_val_a, mac_val_b;

  function [31:0] sext12(input [11:0] x);
    begin
      sext12 = {{20{x[11]}}, x};
    end
  endfunction

  function [31:0] zext12(input [11:0] x);
    begin
      zext12 = {20'b0, x};
    end
  endfunction

  function [31:0] sext13_b(input [12:0] x);
    begin
      sext13_b = {{19{x[12]}}, x};
    end
  endfunction

  function [31:0] sext21_j(input [20:0] x);
    begin
      sext21_j = {{11{x[20]}}, x};
    end
  endfunction

  function [31:0] sext11(input [10:0] x);
    begin
      sext11 = {{21{x[10]}}, x};
    end
  endfunction

  genvar gi;
  generate
    for (gi=0; gi<32; gi=gi+1) begin : G_PACK
      assign regs_o[(31-gi)*32 +: 32] = rfile[gi];
    end
  endgenerate

  integer i;

  wire [6:0] opcode = instr[6:0];
  wire [2:0] funct3 = instr[14:12];
  wire [6:0] funct7 = instr[31:25];
  wire [4:0] rd     = instr[11:7];
  wire [4:0] rs1    = instr[19:15];
  wire [4:0] rs2    = instr[24:20];

  localparam [6:0] OPC_STD_LUI   = 7'b0110111;
  localparam [6:0] OPC_STD_AUIPC = 7'b0010111;
  localparam [6:0] OPC_STD_JAL   = 7'b1101111;
  localparam [6:0] OPC_STD_JALR  = 7'b1100111;
  localparam [6:0] OPC_STD_LOAD  = 7'b0000011;
  localparam [6:0] OPC_STD_STORE = 7'b0100011;
  localparam [6:0] OPC_STD_BR    = 7'b1100011;
  localparam [6:0] OPC_STD_ALUI  = 7'b0010011;
  localparam [6:0] OPC_STD_ALUR  = 7'b0110011;

  localparam [6:0] OPC_C1 = 7'b1110111;
  localparam [6:0] OPC_C2 = 7'b1111111;

  wire op_subabs = (opcode==OPC_C1) && (funct7==7'b0000000) && (funct3==3'b000);
  wire op_avg    = (opcode==OPC_C1) && (funct3==3'b100);
  wire op_movu   = (opcode==OPC_C1) && (funct3==3'b101);
  wire op_srt    = (opcode==OPC_C1) && (funct7==7'b0000010) && (funct3==3'b001);
  wire op_ldmax  = (opcode==OPC_C1) && (funct7==7'b0000100) && (funct3==3'b110);
  wire op_srch   = (opcode==OPC_C1) && (funct7==7'b0001000) && (funct3==3'b111);
  wire op_selp   = (opcode==OPC_C1) && (funct3==3'b010);
  wire op_selc   = (opcode==OPC_C2) && (funct3==3'b000);
  wire op_mac    = (opcode==OPC_C2) && (funct3==3'b111);

  wire [31:0] immI_w = sext12(instr[31:20]);
  wire [31:0] immS_w = sext12({instr[31:25], instr[11:7]});
  wire [12:0] immB_p = {instr[31], instr[7], instr[30:25], instr[11:8], 1'b0};
  wire [31:0] immB_w = sext13_b(immB_p);
  wire [31:0] immU_w = {instr[31:12], 12'b0};
  wire [20:0] immJ_p = {instr[31], instr[19:12], instr[20], instr[30:21], 1'b0};
  wire [31:0] immJ_w = sext21_j(immJ_p);

  wire        sel_s1  = instr[31];
  wire [1:0]  sel_s2  = instr[31:30];

  wire [10:0] immC2_p = {instr[7], instr[29:25], instr[11:8], 1'b0};
  wire [31:0] immC2_w = sext11(immC2_p);

  wire [31:0] canon_i = { inst_i[7:0], inst_i[15:8], inst_i[23:16], inst_i[31:24] };

  always @* begin
    immI_q = immI_w;
    immS_q = immS_w;
    immB_q = immB_w;
    immU_q = immU_w;
    immJ_q = immJ_w;
  end

  always @(posedge clk_i or posedge rst_i) begin
    if (rst_i) begin
      pc_reg          <= 32'd0;
      pc_o            <= 32'd0;
      phase           <= 2'd0;
      cur_stage_o     <= 2'd0;
      instr           <= 32'd0;
      data_mem_we_o   <= 1'b0;
      data_mem_addr_o <= 32'd0;
      data_mem_wdata_o<= 32'd0;
      is_load_q       <= 1'b0;
      is_store_q      <= 1'b0;
      ex_wb_en_q      <= 1'b0;
      ex_result_q     <= 32'd0;
      ex_pc_jump_q    <= 1'b0;
      ex_pc_next_q    <= 32'd0;
      ex_left         <= 8'd0;
      srt_step_q      <= 2'd0;
      ldmax_step_q    <= 2'd0;
      ldmax_rd_q      <= 32'd0;
      ldmax_rs1_q     <= 32'd0;
      ldmax_rs2_q     <= 32'd0;
      mac_active      <= 1'b0;
      mac_addr_accum  <= 32'd0;
      mac_addr_a      <= 32'd0;
      mac_addr_b      <= 32'd0;
      mac_val_a       <= 32'd0;
      mac_val_b       <= 32'd0;
      for (i=0;i<32;i=i+1) rfile[i] <= 32'd0;
    end else begin
      rfile[0] <= 32'd0;

      case (phase)
        2'd0: begin
          cur_stage_o <= 2'd0;
          pc_o        <= pc_reg;
          instr       <= canon_i;
          phase       <= 2'd1;
        end

        2'd1: begin
          cur_stage_o <= 2'd1;
          rd_q        <= rd;
          rs1_q       <= rs1;
          rs2_q       <= rs2;
          rs1_val_q   <= rfile[rs1];
          rs2_val_q   <= rfile[rs2];

          is_load_q   <= (opcode==OPC_STD_LOAD)  && (funct3==3'b010);
          is_store_q  <= (opcode==OPC_STD_STORE) && (funct3==3'b010);

          if (op_srt) begin
            ex_left    <= 8'd2;
            srt_step_q <= 2'd0;
            mac_active <= 1'b0;
          end else if (op_ldmax) begin
            ex_left      <= 8'd3;
            ldmax_step_q <= 2'd0;
            mac_active   <= 1'b0;
          end else if (op_mac) begin
            ex_left        <= ({6'b0, sel_s2} + 8'd1) * 8'd4;
            mac_addr_accum <= immC2_w;
            mac_addr_a     <= rfile[rs1];
            mac_addr_b     <= rfile[rs2];
            mac_val_a      <= 32'd0;
            mac_val_b      <= 32'd0;
            mac_active     <= 1'b1;
          end else begin
            ex_left    <= 8'd0;
            mac_active <= 1'b0;
          end

          ex_wb_en_q   <= 1'b0;
          ex_result_q  <= 32'd0;
          ex_pc_jump_q <= 1'b0;
          ex_pc_next_q <= 32'd0;

          phase <= 2'd2;
        end

        2'd2: begin
          cur_stage_o      <= 2'd2;
          data_mem_we_o    <= 1'b0;
          data_mem_addr_o  <= 32'd0;
          data_mem_wdata_o <= 32'd0;

          if (is_load_q) begin
            data_mem_addr_o <= rs1_val_q + immI_q;
            ex_result_q     <= data_mem_rdata_i;
            ex_wb_en_q      <= (rd_q!=5'd0);
          end
          if (is_store_q) begin
            data_mem_addr_o <= rs1_val_q + immS_q;
            data_mem_wdata_o<= rs2_val_q;
            data_mem_we_o   <= 1'b1;
            ex_wb_en_q      <= 1'b0;
            ex_result_q     <= 32'd0;
          end

          if (op_srt) begin
            if (ex_left > 0) begin
              if (srt_step_q==2'd0) begin
                data_mem_addr_o  <= rfile[rd_q];
                data_mem_wdata_o <= ($signed(rs1_val_q) <= $signed(rs2_val_q)) ? rs1_val_q : rs2_val_q;
                data_mem_we_o    <= 1'b1;
                srt_step_q       <= 2'd1;
              end else begin
                data_mem_addr_o  <= rfile[rd_q] + 32'd4;
                data_mem_wdata_o <= ($signed(rs1_val_q) > $signed(rs2_val_q)) ? rs1_val_q : rs2_val_q;
                data_mem_we_o    <= 1'b1;
              end
              ex_left <= ex_left - 8'd1;
            end
          end else if (op_ldmax) begin
            if (ex_left > 0) begin
              case (ldmax_step_q)
                2'd0: begin
                  data_mem_addr_o <= rfile[rd_q];
                  ldmax_rd_q      <= data_mem_rdata_i;
                  ldmax_step_q    <= 2'd1;
                end
                2'd1: begin
                  data_mem_addr_o <= rfile[rs1_q];
                  ldmax_rs1_q     <= data_mem_rdata_i;
                  ldmax_step_q    <= 2'd2;
                end
                default: begin
                  data_mem_addr_o <= rfile[rs2_q];
                  ldmax_rs2_q     <= data_mem_rdata_i;
                end
              endcase
              ex_left <= ex_left - 8'd1;
            end
            if (ex_left==8'd1) begin
              ex_result_q <= ( ((ldmax_rd_q >= ldmax_rs1_q) ? ldmax_rd_q : ldmax_rs1_q) >= ldmax_rs2_q )
                              ? ((ldmax_rd_q >= ldmax_rs1_q) ? ldmax_rd_q : ldmax_rs1_q)
                              : ldmax_rs2_q;
              ex_wb_en_q  <= (rd_q!=5'd0);
            end
          end else if (mac_active) begin
            if (ex_left > 0) begin
              case ((ex_left-8'd1) & 8'h03)
                8'd3: begin
                  data_mem_addr_o <= mac_addr_a;
                end
                8'd2: begin
                  mac_val_a       <= data_mem_rdata_i;
                  data_mem_addr_o <= mac_addr_b;
                end
                8'd1: begin
                  mac_val_b       <= data_mem_rdata_i;
                  data_mem_addr_o <= mac_addr_accum;
                end
                default: begin
                  data_mem_addr_o  <= mac_addr_accum;
                  data_mem_wdata_o <= data_mem_rdata_i + (mac_val_a * mac_val_b);
                  data_mem_we_o    <= 1'b1;
                  mac_addr_a       <= mac_addr_a + 32'd4;
                  mac_addr_b       <= mac_addr_b + 32'd4;
                end
              endcase
              ex_left <= ex_left - 8'd1;
            end
            if (ex_left==8'd1) begin
              ex_wb_en_q  <= 1'b0;
              ex_result_q <= 32'd0;
            end
          end else begin
            case (opcode)
              OPC_STD_LUI:   begin ex_wb_en_q<=1'b1; ex_result_q<=immU_q; end
              OPC_STD_AUIPC: begin ex_wb_en_q<=1'b1; ex_result_q<=pc_reg + immU_q; end
              OPC_STD_JAL:   begin ex_wb_en_q<= (rd_q!=5'd0); ex_result_q<= pc_reg + 32'd4; ex_pc_jump_q<=1'b1; ex_pc_next_q<= pc_reg + immJ_q; end
              OPC_STD_JALR:  begin ex_wb_en_q<= (rd_q!=5'd0); ex_result_q<= pc_reg + 32'd4; ex_pc_jump_q<=1'b1; ex_pc_next_q<= (rs1_val_q + immI_q) & ~32'd1; end
              OPC_STD_BR: begin
                if ((funct3==3'b000 && (rs1_val_q==rs2_val_q)) ||
                    (funct3==3'b101 && ($signed(rs1_val_q) >= $signed(rs2_val_q)))) begin
                  ex_pc_jump_q <= 1'b1;
                  ex_pc_next_q <= pc_reg + immB_q;
                end
                ex_wb_en_q <= 1'b0;
                ex_result_q<=32'd0;
              end
              OPC_STD_ALUI: begin
                case (funct3)
                  3'b000: begin ex_result_q <= rs1_val_q + immI_q; ex_wb_en_q <= (rd_q!=5'd0); end
                  3'b011: begin ex_result_q <= ($unsigned(rs1_val_q) < $unsigned(immI_q)) ? 32'd1 : 32'd0; ex_wb_en_q <= (rd_q!=5'd0); end
                  3'b100: begin ex_result_q <= rs1_val_q ^ immI_q; ex_wb_en_q <= (rd_q!=5'd0); end
                  3'b001: begin ex_result_q <= rs1_val_q << instr[24:20]; ex_wb_en_q <= (rd_q!=5'd0); end
                  default: begin ex_result_q <= 32'd0; ex_wb_en_q <= 1'b0; end
                endcase
              end
              OPC_STD_ALUR: begin
                if      (funct3==3'b000 && funct7==7'b0000000) begin ex_result_q<= rs1_val_q + rs2_val_q; ex_wb_en_q<=(rd_q!=5'd0); end
                else if (funct3==3'b000 && funct7==7'b0100000) begin ex_result_q<= rs1_val_q - rs2_val_q; ex_wb_en_q<=(rd_q!=5'd0); end
                else if (funct3==3'b010 && funct7==7'b0000000) begin ex_result_q<= ($signed(rs1_val_q) <  $signed(rs2_val_q)) ? 32'd1:32'd0; ex_wb_en_q<=(rd_q!=5'd0); end
                else if (funct3==3'b011 && funct7==7'b0000000) begin ex_result_q<= ($unsigned(rs1_val_q)< $unsigned(rs2_val_q)) ? 32'd1:32'd0; ex_wb_en_q<=(rd_q!=5'd0); end
                else if (funct3==3'b101 && funct7==7'b0100000) begin ex_result_q<= $signed(rs1_val_q) >>> rs2_val_q[4:0]; ex_wb_en_q<=(rd_q!=5'd0); end
                else if (funct3==3'b111 && funct7==7'b0000000) begin ex_result_q<= rs1_val_q & rs2_val_q; ex_wb_en_q<=(rd_q!=5'd0); end
                else begin ex_result_q<=32'd0; ex_wb_en_q<=1'b0; end
              end
              default: begin end
            endcase

            if (op_subabs) begin
              if ($signed(rs1_val_q - rs2_val_q) < 0)
                ex_result_q <= rs2_val_q - rs1_val_q;
              else
                ex_result_q <= rs1_val_q - rs2_val_q;
              ex_wb_en_q  <= (rd_q!=5'd0);
            end
            if (op_avg) begin
              ex_result_q <= $signed(rs1_val_q + immI_q) >>> 1;
              ex_wb_en_q  <= (rd_q!=5'd0);
            end
            if (op_movu) begin
              ex_result_q <= zext12(instr[31:20]);
              ex_wb_en_q  <= (rd_q!=5'd0);
            end
            if (op_srch) begin
              ex_result_q <= ((rfile[rs1_q][7:0]   == rs2_val_q[7:0]) ||
                              (rfile[rs1_q][15:8]  == rs2_val_q[7:0]) ||
                              (rfile[rs1_q][23:16] == rs2_val_q[7:0]) ||
                              (rfile[rs1_q][31:24] == rs2_val_q[7:0])) ? 32'd1 : 32'd0;
              ex_wb_en_q  <= (rd_q!=5'd0);
            end
            if (op_selp) begin
              ex_result_q <= sel_s1 ? {16'b0, rs1_val_q[31:16]} : {16'b0, rs1_val_q[15:0]};
              ex_wb_en_q  <= (rd_q!=5'd0);
            end
            if (op_selc) begin
              if (sel_s2!=2'b11) begin
                if ((sel_s2==2'b00 && (rs1_val_q==rs2_val_q)) ||
                    (sel_s2==2'b01 && ($signed(rs1_val_q) >= $signed(rs2_val_q))) ||
                    (sel_s2==2'b10 && ($signed(rs1_val_q) <  $signed(rs2_val_q)))) begin
                  ex_pc_jump_q <= 1'b1;
                  ex_pc_next_q <= pc_reg + immC2_w;
                end
              end
              ex_wb_en_q <= 1'b0;
              ex_result_q<=32'd0;
            end
          end

          if (op_srt || op_ldmax || mac_active) begin
            phase <= (ex_left==8'd1) ? 2'd3 : 2'd2;
          end else begin
            phase <= 2'd3;
          end
        end

        2'd3: begin
          cur_stage_o <= 2'd3;
          if (ex_wb_en_q && (rd_q!=5'd0)) begin
            rfile[rd_q] <= ex_result_q;
          end
          if (ex_pc_jump_q) begin
            pc_reg <= ex_pc_next_q;
          end else begin
            pc_reg <= pc_reg + 32'd4;
          end

          ex_wb_en_q   <= 1'b0;
          ex_result_q  <= 32'd0;
          ex_pc_jump_q <= 1'b0;
          ex_pc_next_q <= 32'd0;
          phase        <= 2'd0;
        end

        default: begin
          phase <= 2'd0;
        end
      endcase
    end
  end
endmodule

bil361-odev1/tb_ozdemir.v
`timescale 1ns/1ps
module tb_ozdemir;
  reg clk_i = 0;
  reg rst_i = 1;
  wire [31:0] pc_o;
  wire [1023:0] regs_o;
  wire data_mem_we_o;
  wire [31:0] data_mem_addr_o;
  wire [31:0] data_mem_wdata_o;
  reg  [31:0] data_mem_rdata_i;
  reg  [31:0] inst_i;
  wire [1:0]  cur_stage_o;

  ozdemir dut(
    .clk_i(clk_i),
    .rst_i(rst_i),
    .inst_i(inst_i),
    .pc_o(pc_o),
    .regs_o(regs_o),
    .data_mem_we_o(data_mem_we_o),
    .data_mem_addr_o(data_mem_addr_o),
    .data_mem_wdata_o(data_mem_wdata_o),
    .data_mem_rdata_i(data_mem_rdata_i),
    .cur_stage_o(cur_stage_o)
  );

  reg [31:0] rom_le [0:63];
  reg [31:0] dmem   [0:255];

  function [31:0] to_le(input [31:0] w);
    begin
      to_le = {w[7:0], w[15:8], w[23:16], w[31:24]};
    end
  endfunction

  function [31:0] getreg(input [1023:0] bus, input integer idx);
    begin
      getreg = bus[(31-idx)*32 +: 32];
    end
  endfunction

  always #5 clk_i = ~clk_i;

  always @(*) begin
    inst_i = rom_le[pc_o[31:2]];
  end

  always @(*) begin
    data_mem_rdata_i = dmem[data_mem_addr_o[31:2]];
  end

  always @(posedge clk_i) begin
    if (data_mem_we_o) dmem[data_mem_addr_o[31:2]] <= data_mem_wdata_o;
  end

  integer i;
  initial begin
    for (i = 0; i < 64; i = i + 1) rom_le[i] = to_le(32'h00000013);
    for (i = 0; i < 256; i = i + 1) dmem[i] = 32'h00000000;

    rom_le[0] = to_le(32'h000120B7);
    rom_le[1] = to_le(32'h00508093);
    rom_le[2] = to_le(32'h00102023);
    rom_le[3] = to_le(32'h00002103);
    rom_le[4] = to_le(32'h0020F1B3);

    $dumpfile("chk.vcd");
    $dumpvars(0, tb_ozdemir);

    #20 rst_i = 0;
    #400;

    if (dmem[0] !== 32'h00012005) $fatal(1, "DMEM_MISMATCH");
    if (getreg(regs_o, 1) !== 32'h00012005) $fatal(1, "X1_MISMATCH");
    if (getreg(regs_o, 2) !== 32'h00012005) $fatal(1, "X2_MISMATCH");
    if (getreg(regs_o, 3) !== 32'h00012005) $fatal(1, "X3_MISMATCH");

    $display("PASS");
    $finish;
  end
endmodule

bil361-odev1/chk.vcd
$date
	Mon Nov 24 18:27:39 2025
$end
$version
	Icarus Verilog
$end
$timescale
	1ps
$end
$scope module tb_ozdemir $end
$var wire 1024 ! regs_o [1023:0] $end
$var wire 32 " pc_o [31:0] $end
$var wire 1 # data_mem_we_o $end
$var wire 32 $ data_mem_wdata_o [31:0] $end
$var wire 32 % data_mem_addr_o [31:0] $end
$var wire 2 & cur_stage_o [1:0] $end
$var reg 1 ' clk_i $end
$var reg 32 ( data_mem_rdata_i [31:0] $end
$var reg 32 ) inst_i [31:0] $end
$var reg 1 * rst_i $end
$var integer 32 + i [31:0] $end
$scope function getreg $end
$var reg 1024 , bus [1023:0] $end
$var integer 32 - idx [31:0] $end
$upscope $end
$scope function to_le $end
$var reg 32 . w [31:0] $end
$upscope $end
$scope module dut $end
$var wire 1 ' clk_i $end
$var wire 32 / data_mem_rdata_i [31:0] $end
$var wire 32 0 inst_i [31:0] $end
$var wire 1 1 op_avg $end
$var wire 1 2 op_ldmax $end
$var wire 1 3 op_mac $end
$var wire 1 4 op_movu $end
$var wire 1 5 op_selc $end
$var wire 1 6 op_selp $end
$var wire 1 7 op_srch $end
$var wire 1 8 op_srt $end
$var wire 1 9 op_subabs $end
$var wire 1 * rst_i $end
$var wire 2 : sel_s2 [1:0] $end
$var wire 1 ; sel_s1 $end
$var wire 5 < rs2 [4:0] $end
$var wire 5 = rs1 [4:0] $end
$var wire 1024 > regs_o [1023:0] $end
$var wire 5 ? rd [4:0] $end
$var wire 7 @ opcode [6:0] $end
$var wire 32 A immU_w [31:0] $end
$var wire 32 B immS_w [31:0] $end
$var wire 32 C immJ_w [31:0] $end
$var wire 21 D immJ_p [20:0] $end
$var wire 32 E immI_w [31:0] $end
$var wire 32 F immC2_w [31:0] $end
$var wire 11 G immC2_p [10:0] $end
$var wire 32 H immB_w [31:0] $end
$var wire 13 I immB_p [12:0] $end
$var wire 7 J funct7 [6:0] $end
$var wire 3 K funct3 [2:0] $end
$var wire 32 L canon_i [31:0] $end
$var parameter 7 M OPC_C1 $end
$var parameter 7 N OPC_C2 $end
$var parameter 7 O OPC_STD_ALUI $end
$var parameter 7 P OPC_STD_ALUR $end
$var parameter 7 Q OPC_STD_AUIPC $end
$var parameter 7 R OPC_STD_BR $end
$var parameter 7 S OPC_STD_JAL $end
$var parameter 7 T OPC_STD_JALR $end
$var parameter 7 U OPC_STD_LOAD $end
$var parameter 7 V OPC_STD_LUI $end
$var parameter 7 W OPC_STD_STORE $end
$var reg 2 X cur_stage_o [1:0] $end
$var reg 32 Y data_mem_addr_o [31:0] $end
$var reg 32 Z data_mem_wdata_o [31:0] $end
$var reg 1 # data_mem_we_o $end
$var reg 8 [ ex_left [7:0] $end
$var reg 1 \ ex_pc_jump_q $end
$var reg 32 ] ex_pc_next_q [31:0] $end
$var reg 32 ^ ex_result_q [31:0] $end
$var reg 1 _ ex_wb_en_q $end
$var reg 32 ` immB_q [31:0] $end
$var reg 32 a immI_q [31:0] $end
$var reg 32 b immJ_q [31:0] $end
$var reg 32 c immS_q [31:0] $end
$var reg 32 d immU_q [31:0] $end
$var reg 32 e instr [31:0] $end
$var reg 1 f is_load_q $end
$var reg 1 g is_store_q $end
$var reg 32 h ldmax_rd_q [31:0] $end
$var reg 32 i ldmax_rs1_q [31:0] $end
$var reg 32 j ldmax_rs2_q [31:0] $end
$var reg 2 k ldmax_step_q [1:0] $end
$var reg 1 l mac_active $end
$var reg 32 m mac_addr_a [31:0] $end
$var reg 32 n mac_addr_accum [31:0] $end
$var reg 32 o mac_addr_b [31:0] $end
$var reg 32 p mac_val_a [31:0] $end
$var reg 32 q mac_val_b [31:0] $end
$var reg 32 r pc_o [31:0] $end
$var reg 32 s pc_reg [31:0] $end
$var reg 2 t phase [1:0] $end
$var reg 5 u rd_q [4:0] $end
$var reg 5 v rs1_q [4:0] $end
$var reg 32 w rs1_val_q [31:0] $end
$var reg 5 x rs2_q [4:0] $end
$var reg 32 y rs2_val_q [31:0] $end
$var reg 2 z srt_step_q [1:0] $end
$var integer 32 { i [31:0] $end
$scope function sext11 $end
$var reg 11 | x [10:0] $end
$upscope $end
$scope function sext12 $end
$var reg 12 } x [11:0] $end
$upscope $end
$scope function sext13_b $end
$var reg 13 ~ x [12:0] $end
$upscope $end
$scope function sext21_j $end
$var reg 21 !" x [20:0] $end
$upscope $end
$scope function zext12 $end
$var reg 12 "" x [11:0] $end
$upscope $end
$scope begin G_PACK[0] $end
$var parameter 2 #" gi $end
$upscope $end
$scope begin G_PACK[1] $end
$var parameter 2 $" gi $end
$upscope $end
$scope begin G_PACK[2] $end
$var parameter 3 %" gi $end
$upscope $end
$scope begin G_PACK[3] $end
$var parameter 3 &" gi $end
$upscope $end
$scope begin G_PACK[4] $end
$var parameter 4 '" gi $end
$upscope $end
$scope begin G_PACK[5] $end
$var parameter 4 (" gi $end
$upscope $end
$scope begin G_PACK[6] $end
$var parameter 4 )" gi $end
$upscope $end
$scope begin G_PACK[7] $end
$var parameter 4 *" gi $end
$upscope $end
$scope begin G_PACK[8] $end
$var parameter 5 +" gi $end
$upscope $end
$scope begin G_PACK[9] $end
$var parameter 5 ," gi $end
$upscope $end
$scope begin G_PACK[10] $end
$var parameter 5 -" gi $end
$upscope $end
$scope begin G_PACK[11] $end
$var parameter 5 ." gi $end
$upscope $end
$scope begin G_PACK[12] $end
$var parameter 5 /" gi $end
$upscope $end
$scope begin G_PACK[13] $end
$var parameter 5 0" gi $end
$upscope $end
$scope begin G_PACK[14] $end
$var parameter 5 1" gi $end
$upscope $end
$scope begin G_PACK[15] $end
$var parameter 5 2" gi $end
$upscope $end
$scope begin G_PACK[16] $end
$var parameter 6 3" gi $end
$upscope $end
$scope begin G_PACK[17] $end
$var parameter 6 4" gi $end
$upscope $end
$scope begin G_PACK[18] $end
$var parameter 6 5" gi $end
$upscope $end
$scope begin G_PACK[19] $end
$var parameter 6 6" gi $end
$upscope $end
$scope begin G_PACK[20] $end
$var parameter 6 7" gi $end
$upscope $end
$scope begin G_PACK[21] $end
$var parameter 6 8" gi $end
$upscope $end
$scope begin G_PACK[22] $end
$var parameter 6 9" gi $end
$upscope $end
$scope begin G_PACK[23] $end
$var parameter 6 :" gi $end
$upscope $end
$scope begin G_PACK[24] $end
$var parameter 6 ;" gi $end
$upscope $end
$scope begin G_PACK[25] $end
$var parameter 6 <" gi $end
$upscope $end
$scope begin G_PACK[26] $end
$var parameter 6 =" gi $end
$upscope $end
$scope begin G_PACK[27] $end
$var parameter 6 >" gi $end
$upscope $end
$scope begin G_PACK[28] $end
$var parameter 6 ?" gi $end
$upscope $end
$scope begin G_PACK[29] $end
$var parameter 6 @" gi $end
$upscope $end
$scope begin G_PACK[30] $end
$var parameter 6 A" gi $end
$upscope $end
$scope begin G_PACK[31] $end
$var parameter 6 B" gi $end
$upscope $end
$upscope $end
$upscope $end
$enddefinitions $end
$comment Show the parameter values. $end
$dumpall
b11111 B"
b11110 A"
b11101 @"
b11100 ?"
b11011 >"
b11010 ="
b11001 <"
b11000 ;"
b10111 :"
b10110 9"
b10101 8"
b10100 7"
b10011 6"
b10010 5"
b10001 4"
b10000 3"
b1111 2"
b1110 1"
b1101 0"
b1100 /"
b1011 ."
b1010 -"
b1001 ,"
b1000 +"
b111 *"
b110 )"
b101 ("
b100 '"
b11 &"
b10 %"
b1 $"
b0 #"
b100011 W
b110111 V
b11 U
b1100111 T
b1101111 S
b1100011 R
b10111 Q
b110011 P
b10011 O
b1111111 N
b1110111 M
$end
#0
$dumpvars
bx ""
b0 !"
b0 ~
b0 }
b0 |
b100000 {
b0 z
bx y
bx x
bx w
bx v
bx u
b0 t
b0 s
b0 r
b0 q
b0 p
b0 o
b0 n
b0 m
0l
b0 k
b0 j
b0 i
b0 h
0g
0f
b0 e
b0 d
b0 c
b0 b
b0 a
b0 `
0_
b0 ^
b0 ]
0\
b0 [
b0 Z
b0 Y
b0 X
b10010000010110111 L
b0 K
b0 J
b0 I
b0 H
b0 G
b0 F
b0 E
b0 D
b0 C
b0 B
b0 A
b0 @
b0 ?
b0 >
b0 =
b0 <
0;
b0 :
09
08
07
06
05
04
03
02
01
b10110111001000000000000100000000 0
b0 /
b1000001111000110110011 .
bx -
bx ,
b100000000 +
1*
b10110111001000000000000100000000 )
b0 (
0'
b0 &
b0 %
b0 $
0#
b0 "
b0 !
$end
#5000
b100000 {
1'
#10000
0'
#15000
b100000 {
1'
#20000
0'
0*
#25000
b100000000000 `
b1 c
b1 B
b1 }
b100000000000 H
b100000000000 ~
b10010000000000000 b
b10010000000000000 d
b10010000000000000 C
b10010000000000000 !"
b11111111111111111111110000000000 F
b10000000000 |
b110111 @
b10 K
b1 ?
b10 =
b100000000000 I
b10010000000000000 A
b10010000000000000 D
b10000000000 G
b1 t
b10010000010110111 e
1'
#30000
0'
#35000
b10 t
b0 y
b0 w
b0 x
b10 v
b1 u
b1 &
b1 X
1'
#40000
0'
#45000
b11 t
b10010000000000000 ^
1_
b10 &
b10 X
1'
#50000
0'
#55000
b0 t
b0 ^
0_
b100 s
b10010000000000000000000000000000000000000000000000000000000000000000000000000000000000000000000000000000000000000000000000000000000000000000000000000000000000000000000000000000000000000000000000000000000000000000000000000000000000000000000000000000000000000000000000000000000000000000000000000000000000000000000000000000000000000000000000000000000000000000000000000000000000000000000000000000000000000000000000000000000000000000000000000000000000000000000000000000000000000000000000000000000000000000000000000000000000000000000000000000000000000000000000000000000000000000000000000000000000000000000000000000000000000000000000000000000000000000000000000000000000000000000000000000000000000000000000000000000000000000000000000000000000000000000000000000000000000000000000000000000000000000000000000000000000000000000000000000000000000000000000000000000000000000000000000000000000000000000000000000000000000000000000000000000000000000000000000000000000000000000000000000000000000 !
b10010000000000000000000000000000000000000000000000000000000000000000000000000000000000000000000000000000000000000000000000000000000000000000000000000000000000000000000000000000000000000000000000000000000000000000000000000000000000000000000000000000000000000000000000000000000000000000000000000000000000000000000000000000000000000000000000000000000000000000000000000000000000000000000000000000000000000000000000000000000000000000000000000000000000000000000000000000000000000000000000000000000000000000000000000000000000000000000000000000000000000000000000000000000000000000000000000000000000000000000000000000000000000000000000000000000000000000000000000000000000000000000000000000000000000000000000000000000000000000000000000000000000000000000000000000000000000000000000000000000000000000000000000000000000000000000000000000000000000000000000000000000000000000000000000000000000000000000000000000000000000000000000000000000000000000000000000000000000000000000000000000000000000 >
b11 &
b11 X
1'
#60000
0'
#65000
b10100001000000010010011 L
b10010011100000000101000000000000 )
b10010011100000000101000000000000 0
b1 t
b100 "
b100 r
b0 &
b0 X
1'
#70000
0'
#75000
b10 t
b1 &
b1 X
1'
#80000
0'
#85000
b11 t
b10010000000000000 ^
1_
b10 &
b10 X
1'
#90000
0'
#95000
b0 t
b0 ^
0_
b1000 s
b11 &
b11 X
1'
#100000
0'
#105000
b101 a
b101 E
b101 }
b1000100000000100 b
b10100001000000000000000 d
b1000100000000100 C
b1000100000000100 !"
b100000010000000100011 L
b10011 @
b0 K
b1 =
b101 <
b10100001000000000000000 A
b1000100000000100 D
b100011001000000001000000000000 )
b100011001000000001000000000000 0
b1 t
b10100001000000010010011 e
b1000 "
b1000 r
b0 &
b0 X
1'
#110000
0'
#115000
b10 t
b10010000000000000 w
b101 x
b1 v
b1 &
b1 X
1'
#120000
0'
#125000
b11 t
1_
b10010000000000101 ^
b10 &
b10 X
1'
#130000
0'
